spatialstudio/__init__.py
spatialstudio/splv/__init__.py
spatialstudio/splv/libsplv_py.cpython-39-x86_64-linux-gnu.so
spatialstudio-1.1.1.34.dist-info/METADATA
spatialstudio-1.1.1.34.dist-info/WHEEL
spatialstudio-1.1.1.34.dist-info/top_level.txt
spatialstudio-1.1.1.34.dist-info/RECORD
