Metadata-Version: 2.4
Name: spatialstudio
Version: 1.1.1.34
Summary: Utilities for creating Spatials (4D videos)
Author-email: Daniel Elwell <de@true3d.com>, Sumanta Das <sumanta@true3d.com>
License-Expression: MIT
Project-URL: Homepage, https://github.com/SpatialDeploy/SpatialStudio
Project-URL: Repository, https://github.com/SpatialDeploy/SpatialStudio
Project-URL: Issues, https://github.com/SpatialDeploy/SpatialStudio/issues
Classifier: Intended Audience :: Developers
Classifier: Operating System :: OS Independent
Classifier: Programming Language :: Python :: 3
Classifier: Programming Language :: Python :: 3.9
Classifier: Programming Language :: Python :: 3.10
Classifier: Programming Language :: Python :: 3.11
Classifier: Programming Language :: Python :: 3.12
Classifier: Programming Language :: Python :: 3.13
Requires-Python: >=3.9
